setup.py
Clutch.egg-info/PKG-INFO
Clutch.egg-info/SOURCES.txt
Clutch.egg-info/dependency_links.txt
Clutch.egg-info/entry_points.txt
Clutch.egg-info/not-zip-safe
Clutch.egg-info/requires.txt
Clutch.egg-info/top_level.txt
clutch/__init__.py
clutch/blob.py
clutch/controllers.py
clutch/dottedtemplatelookup.py
clutch/lib.py
clutch/render.py
clutch/validation.py
clutch/wsgiapp.py
clutch/forms/__init__.py
clutch/forms/core.py
clutch/forms/seekable.py