Metadata-Version: 1.0
Name: Clutch
Version: 0.1a2
Summary: A Python Web Framework for GAE
Home-page: http://getclutch.appspot.com
Author: Lee McFadden
Author-email: spleeman@gmail.com
License: MIT
Platform: UNKNOWN
Classifier: Development Status :: 3 - Alpha
Classifier: Intended Audience :: Developers
Classifier: License :: OSI Approved :: MIT License
Classifier: Natural Language :: English
Classifier: Operating System :: OS Independent
Classifier: Programming Language :: Python
Classifier: Topic :: Internet :: WWW/HTTP
Classifier: Topic :: Software Development :: Libraries :: Python Modules
